{"nodes": [{"id": "backend_app_api_knowledge_map_py", "label": "knowledge_map.py", "file_type": "code", "source_file": "backend/app/api/knowledge_map.py", "source_location": "L1"}, {"id": "knowledge_map_rangecountsresponse", "label": "RangeCountsResponse", "file_type": "code", "source_file": "backend/app/api/knowledge_map.py", "source_location": "L66"}, {"id": "basemodel", "label": "BaseModel", "file_type": "code", "source_file": "", "source_location": ""}, {"id": "knowledge_map_overviewrangeresponse", "label": "OverviewRangeResponse", "file_type": "code", "source_file": "backend/app/api/knowledge_map.py", "source_location": "L73"}, {"id": "knowledge_map_knowledgemapoverviewresponse", "label": "KnowledgeMapOverviewResponse", "file_type": "code", "source_file": "backend/app/api/knowledge_map.py", "source_location": "L80"}, {"id": "knowledge_map_knowledgemapadjacententryresponse", "label": "KnowledgeMapAdjacentEntryResponse", "file_type": "code", "source_file": "backend/app/api/knowledge_map.py", "source_location": "L86"}, {"id": "knowledge_map_knowledgemapdashboardresponse", "label": "KnowledgeMapDashboardResponse", "file_type": "code", "source_file": "backend/app/api/knowledge_map.py", "source_location": "L94"}, {"id": "knowledge_map_knowledgemapentrysummary", "label": "KnowledgeMapEntrySummary", "file_type": "code", "source_file": "backend/app/api/knowledge_map.py", "source_location": "L103"}, {"id": "knowledge_map_knowledgemaprangeresponse", "label": "KnowledgeMapRangeResponse", "file_type": "code", "source_file": "backend/app/api/knowledge_map.py", "source_location": "L122"}, {"id": "knowledge_map_knowledgemapsearchresponse", "label": "KnowledgeMapSearchResponse", "file_type": "code", "source_file": "backend/app/api/knowledge_map.py", "source_location": "L130"}, {"id": "knowledge_map_knowledgemaplistresponse", "label": "KnowledgeMapListResponse", "file_type": "code", "source_file": "backend/app/api/knowledge_map.py", "source_location": "L134"}, {"id": "knowledge_map_meaningexampleresponse", "label": "MeaningExampleResponse", "file_type": "code", "source_file": "backend/app/api/knowledge_map.py", "source_location": "L138"}, {"id": "knowledge_map_learnervoiceassetresponse", "label": "LearnerVoiceAssetResponse", "file_type": "code", "source_file": "backend/app/api/knowledge_map.py", "source_location": "L146"}, {"id": "knowledge_map_translationresponse", "label": "TranslationResponse", "file_type": "code", "source_file": "backend/app/api/knowledge_map.py", "source_location": "L175"}, {"id": "knowledge_map_relationresponse", "label": "RelationResponse", "file_type": "code", "source_file": "backend/app/api/knowledge_map.py", "source_location": "L183"}, {"id": "knowledge_map_relationgroupresponse", "label": "RelationGroupResponse", "file_type": "code", "source_file": "backend/app/api/knowledge_map.py", "source_location": "L189"}, {"id": "knowledge_map_confusablewordresponse", "label": "ConfusableWordResponse", "file_type": "code", "source_file": "backend/app/api/knowledge_map.py", "source_location": "L194"}, {"id": "knowledge_map_inlinelinkedentryresponse", "label": "InlineLinkedEntryResponse", "file_type": "code", "source_file": "backend/app/api/knowledge_map.py", "source_location": "L200"}, {"id": "knowledge_map_linktargetresponse", "label": "LinkTargetResponse", "file_type": "code", "source_file": "backend/app/api/knowledge_map.py", "source_location": "L206"}, {"id": "knowledge_map_linkedtextresponse", "label": "LinkedTextResponse", "file_type": "code", "source_file": "backend/app/api/knowledge_map.py", "source_location": "L212"}, {"id": "knowledge_map_wordformsresponse", "label": "WordFormsResponse", "file_type": "code", "source_file": "backend/app/api/knowledge_map.py", "source_location": "L217"}, {"id": "knowledge_map_knowledgemeaningresponse", "label": "KnowledgeMeaningResponse", "file_type": "code", "source_file": "backend/app/api/knowledge_map.py", "source_location": "L225"}, {"id": "knowledge_map_phrasesenseresponse", "label": "PhraseSenseResponse", "file_type": "code", "source_file": "backend/app/api/knowledge_map.py", "source_location": "L246"}, {"id": "knowledge_map_adjacententryresponse", "label": "AdjacentEntryResponse", "file_type": "code", "source_file": "backend/app/api/knowledge_map.py", "source_location": "L265"}, {"id": "knowledge_map_reviewscheduleoptionresponse", "label": "ReviewScheduleOptionResponse", "file_type": "code", "source_file": "backend/app/api/knowledge_map.py", "source_location": "L271"}, {"id": "knowledge_map_entryreviewqueueresponse", "label": "EntryReviewQueueResponse", "file_type": "code", "source_file": "backend/app/api/knowledge_map.py", "source_location": "L277"}, {"id": "knowledge_map_serialize_model", "label": "serialize_model()", "file_type": "code", "source_file": "backend/app/api/knowledge_map.py", "source_location": "L288"}, {"id": "knowledge_map_knowledgemapdetailresponse", "label": "KnowledgeMapDetailResponse", "file_type": "code", "source_file": "backend/app/api/knowledge_map.py", "source_location": "L309"}, {"id": "knowledge_map_statusupdaterequest", "label": "StatusUpdateRequest", "file_type": "code", "source_file": "backend/app/api/knowledge_map.py", "source_location": "L333"}, {"id": "knowledge_map_validate_status", "label": "validate_status()", "file_type": "code", "source_file": "backend/app/api/knowledge_map.py", "source_location": "L338"}, {"id": "knowledge_map_statusresponse", "label": "StatusResponse", "file_type": "code", "source_file": "backend/app/api/knowledge_map.py", "source_location": "L344"}, {"id": "knowledge_map_searchhistorywriterequest", "label": "SearchHistoryWriteRequest", "file_type": "code", "source_file": "backend/app/api/knowledge_map.py", "source_location": "L350"}, {"id": "knowledge_map_validate_query", "label": "validate_query()", "file_type": "code", "source_file": "backend/app/api/knowledge_map.py", "source_location": "L357"}, {"id": "knowledge_map_validate_entry_type", "label": "validate_entry_type()", "file_type": "code", "source_file": "backend/app/api/knowledge_map.py", "source_location": "L365"}, {"id": "knowledge_map_searchhistoryitemresponse", "label": "SearchHistoryItemResponse", "file_type": "code", "source_file": "backend/app/api/knowledge_map.py", "source_location": "L371"}, {"id": "knowledge_map_searchhistorylistresponse", "label": "SearchHistoryListResponse", "file_type": "code", "source_file": "backend/app/api/knowledge_map.py", "source_location": "L378"}, {"id": "knowledge_map_summary_from_item", "label": "_summary_from_item()", "file_type": "code", "source_file": "backend/app/api/knowledge_map.py", "source_location": "L382"}, {"id": "knowledge_map_voice_asset_response", "label": "_voice_asset_response()", "file_type": "code", "source_file": "backend/app/api/knowledge_map.py", "source_location": "L403"}, {"id": "knowledge_map_load_summary_voice_assets", "label": "_load_summary_voice_assets()", "file_type": "code", "source_file": "backend/app/api/knowledge_map.py", "source_location": "L434"}, {"id": "knowledge_map_adjacent_entry", "label": "_adjacent_entry()", "file_type": "code", "source_file": "backend/app/api/knowledge_map.py", "source_location": "L470"}, {"id": "knowledge_map_dashboard_entry", "label": "_dashboard_entry()", "file_type": "code", "source_file": "backend/app/api/knowledge_map.py", "source_location": "L480"}, {"id": "knowledge_map_finalize_knowledge_map_metrics", "label": "_finalize_knowledge_map_metrics()", "file_type": "code", "source_file": "backend/app/api/knowledge_map.py", "source_location": "L492"}, {"id": "knowledge_map_hydrate_summary_items", "label": "_hydrate_summary_items()", "file_type": "code", "source_file": "backend/app/api/knowledge_map.py", "source_location": "L517"}, {"id": "knowledge_map_get_knowledge_map_overview", "label": "get_knowledge_map_overview()", "file_type": "code", "source_file": "backend/app/api/knowledge_map.py", "source_location": "L576"}, {"id": "knowledge_map_get_knowledge_map_dashboard", "label": "get_knowledge_map_dashboard()", "file_type": "code", "source_file": "backend/app/api/knowledge_map.py", "source_location": "L595"}, {"id": "knowledge_map_get_knowledge_map_list", "label": "get_knowledge_map_list()", "file_type": "code", "source_file": "backend/app/api/knowledge_map.py", "source_location": "L621"}, {"id": "knowledge_map_get_knowledge_map_range", "label": "get_knowledge_map_range()", "file_type": "code", "source_file": "backend/app/api/knowledge_map.py", "source_location": "L666"}, {"id": "knowledge_map_get_knowledge_map_entry_detail", "label": "get_knowledge_map_entry_detail()", "file_type": "code", "source_file": "backend/app/api/knowledge_map.py", "source_location": "L698"}, {"id": "knowledge_map_put_knowledge_map_status", "label": "put_knowledge_map_status()", "file_type": "code", "source_file": "backend/app/api/knowledge_map.py", "source_location": "L1117"}, {"id": "knowledge_map_search_knowledge_map", "label": "search_knowledge_map()", "file_type": "code", "source_file": "backend/app/api/knowledge_map.py", "source_location": "L1165"}, {"id": "knowledge_map_get_search_history", "label": "get_search_history()", "file_type": "code", "source_file": "backend/app/api/knowledge_map.py", "source_location": "L1186"}, {"id": "knowledge_map_post_search_history", "label": "post_search_history()", "file_type": "code", "source_file": "backend/app/api/knowledge_map.py", "source_location": "L1215"}], "edges": [{"source": "backend_app_api_knowledge_map_py", "target": "uuid", "relation": "imports", "confidence": "EXTRACTED", "source_file": "backend/app/api/knowledge_map.py", "source_location": "L1", "weight": 1.0}, {"source": "backend_app_api_knowledge_map_py", "target": "time", "relation": "imports_from", "confidence": "EXTRACTED", "source_file": "backend/app/api/knowledge_map.py", "source_location": "L2", "weight": 1.0}, {"source": "backend_app_api_knowledge_map_py", "target": "fastapi", "relation": "imports_from", "confidence": "EXTRACTED", "source_file": "backend/app/api/knowledge_map.py", "source_location": "L4", "weight": 1.0}, {"source": "backend_app_api_knowledge_map_py", "target": "pydantic", "relation": "imports_from", "confidence": "EXTRACTED", "source_file": "backend/app/api/knowledge_map.py", "source_location": "L5", "weight": 1.0}, {"source": "backend_app_api_knowledge_map_py", "target": "sqlalchemy", "relation": "imports_from", "confidence": "EXTRACTED", "source_file": "backend/app/api/knowledge_map.py", "source_location": "L6", "weight": 1.0}, {"source": "backend_app_api_knowledge_map_py", "target": "sqlalchemy_ext_asyncio", "relation": "imports_from", "confidence": "EXTRACTED", "source_file": "backend/app/api/knowledge_map.py", "source_location": "L7", "weight": 1.0}, {"source": "backend_app_api_knowledge_map_py", "target": "sqlalchemy_orm", "relation": "imports_from", "confidence": "EXTRACTED", "source_file": "backend/app/api/knowledge_map.py", "source_location": "L8", "weight": 1.0}, {"source": "backend_app_api_knowledge_map_py", "target": "app_api_auth", "relation": "imports_from", "confidence": "EXTRACTED", "source_file": "backend/app/api/knowledge_map.py", "source_location": "L10", "weight": 1.0}, {"source": "backend_app_api_knowledge_map_py", "target": "app_api_request_db_metrics", "relation": "imports_from", "confidence": "EXTRACTED", "source_file": "backend/app/api/knowledge_map.py", "source_location": "L11", "weight": 1.0}, {"source": "backend_app_api_knowledge_map_py", "target": "app_core_database", "relation": "imports_from", "confidence": "EXTRACTED", "source_file": "backend/app/api/knowledge_map.py", "source_location": "L12", "weight": 1.0}, {"source": "backend_app_api_knowledge_map_py", "target": "app_core_logging", "relation": "imports_from", "confidence": "EXTRACTED", "source_file": "backend/app/api/knowledge_map.py", "source_location": "L13", "weight": 1.0}, {"source": "backend_app_api_knowledge_map_py", "target": "app_models_learner_entry_status", "relation": "imports_from", "confidence": "EXTRACTED", "source_file": "backend/app/api/knowledge_map.py", "source_location": "L14", "weight": 1.0}, {"source": "backend_app_api_knowledge_map_py", "target": "app_models_meaning", "relation": "imports_from", "confidence": "EXTRACTED", "source_file": "backend/app/api/knowledge_map.py", "source_location": "L15", "weight": 1.0}, {"source": "backend_app_api_knowledge_map_py", "target": "app_models_lexicon_voice_asset", "relation": "imports_from", "confidence": "EXTRACTED", "source_file": "backend/app/api/knowledge_map.py", "source_location": "L16", "weight": 1.0}, {"source": "backend_app_api_knowledge_map_py", "target": "app_models_phrase_entry", "relation": "imports_from", "confidence": "EXTRACTED", "source_file": "backend/app/api/knowledge_map.py", "source_location": "L17", "weight": 1.0}, {"source": "backend_app_api_knowledge_map_py", "target": "app_models_search_history", "relation": "imports_from", "confidence": "EXTRACTED", "source_file": "backend/app/api/knowledge_map.py", "source_location": "L18", "weight": 1.0}, {"source": "backend_app_api_knowledge_map_py", "target": "app_models_user", "relation": "imports_from", "confidence": "EXTRACTED", "source_file": "backend/app/api/knowledge_map.py", "source_location": "L19", "weight": 1.0}, {"source": "backend_app_api_knowledge_map_py", "target": "app_models_word", "relation": "imports_from", "confidence": "EXTRACTED", "source_file": "backend/app/api/knowledge_map.py", "source_location": "L20", "weight": 1.0}, {"source": "backend_app_api_knowledge_map_py", "target": "app_services_knowledge_map", "relation": "imports_from", "confidence": "EXTRACTED", "source_file": "backend/app/api/knowledge_map.py", "source_location": "L21", "weight": 1.0}, {"source": "backend_app_api_knowledge_map_py", "target": "app_services_review", "relation": "imports_from", "confidence": "EXTRACTED", "source_file": "backend/app/api/knowledge_map.py", "source_location": "L53", "weight": 1.0}, {"source": "backend_app_api_knowledge_map_py", "target": "app_services_voice_assets", "relation": "imports_from", "confidence": "EXTRACTED", "source_file": "backend/app/api/knowledge_map.py", "source_location": "L54", "weight": 1.0}, {"source": "backend_app_api_knowledge_map_py", "target": "knowledge_map_rangecountsresponse", "relation": "contains", "confidence": "EXTRACTED", "source_file": "backend/app/api/knowledge_map.py", "source_location": "L66", "weight": 1.0}, {"source": "knowledge_map_rangecountsresponse", "target": "basemodel", "relation": "inherits", "confidence": "EXTRACTED", "source_file": "backend/app/api/knowledge_map.py", "source_location": "L66", "weight": 1.0}, {"source": "backend_app_api_knowledge_map_py", "target": "knowledge_map_overviewrangeresponse", "relation": "contains", "confidence": "EXTRACTED", "source_file": "backend/app/api/knowledge_map.py", "source_location": "L73", "weight": 1.0}, {"source": "knowledge_map_overviewrangeresponse", "target": "basemodel", "relation": "inherits", "confidence": "EXTRACTED", "source_file": "backend/app/api/knowledge_map.py", "source_location": "L73", "weight": 1.0}, {"source": "backend_app_api_knowledge_map_py", "target": "knowledge_map_knowledgemapoverviewresponse", "relation": "contains", "confidence": "EXTRACTED", "source_file": "backend/app/api/knowledge_map.py", "source_location": "L80", "weight": 1.0}, {"source": "knowledge_map_knowledgemapoverviewresponse", "target": "basemodel", "relation": "inherits", "confidence": "EXTRACTED", "source_file": "backend/app/api/knowledge_map.py", "source_location": "L80", "weight": 1.0}, {"source": "backend_app_api_knowledge_map_py", "target": "knowledge_map_knowledgemapadjacententryresponse", "relation": "contains", "confidence": "EXTRACTED", "source_file": "backend/app/api/knowledge_map.py", "source_location": "L86", "weight": 1.0}, {"source": "knowledge_map_knowledgemapadjacententryresponse", "target": "basemodel", "relation": "inherits", "confidence": "EXTRACTED", "source_file": "backend/app/api/knowledge_map.py", "source_location": "L86", "weight": 1.0}, {"source": "backend_app_api_knowledge_map_py", "target": "knowledge_map_knowledgemapdashboardresponse", "relation": "contains", "confidence": "EXTRACTED", "source_file": "backend/app/api/knowledge_map.py", "source_location": "L94", "weight": 1.0}, {"source": "knowledge_map_knowledgemapdashboardresponse", "target": "basemodel", "relation": "inherits", "confidence": "EXTRACTED", "source_file": "backend/app/api/knowledge_map.py", "source_location": "L94", "weight": 1.0}, {"source": "backend_app_api_knowledge_map_py", "target": "knowledge_map_knowledgemapentrysummary", "relation": "contains", "confidence": "EXTRACTED", "source_file": "backend/app/api/knowledge_map.py", "source_location": "L103", "weight": 1.0}, {"source": "knowledge_map_knowledgemapentrysummary", "target": "basemodel", "relation": "inherits", "confidence": "EXTRACTED", "source_file": "backend/app/api/knowledge_map.py", "source_location": "L103", "weight": 1.0}, {"source": "backend_app_api_knowledge_map_py", "target": "knowledge_map_knowledgemaprangeresponse", "relation": "contains", "confidence": "EXTRACTED", "source_file": "backend/app/api/knowledge_map.py", "source_location": "L122", "weight": 1.0}, {"source": "knowledge_map_knowledgemaprangeresponse", "target": "basemodel", "relation": "inherits", "confidence": "EXTRACTED", "source_file": "backend/app/api/knowledge_map.py", "source_location": "L122", "weight": 1.0}, {"source": "backend_app_api_knowledge_map_py", "target": "knowledge_map_knowledgemapsearchresponse", "relation": "contains", "confidence": "EXTRACTED", "source_file": "backend/app/api/knowledge_map.py", "source_location": "L130", "weight": 1.0}, {"source": "knowledge_map_knowledgemapsearchresponse", "target": "basemodel", "relation": "inherits", "confidence": "EXTRACTED", "source_file": "backend/app/api/knowledge_map.py", "source_location": "L130", "weight": 1.0}, {"source": "backend_app_api_knowledge_map_py", "target": "knowledge_map_knowledgemaplistresponse", "relation": "contains", "confidence": "EXTRACTED", "source_file": "backend/app/api/knowledge_map.py", "source_location": "L134", "weight": 1.0}, {"source": "knowledge_map_knowledgemaplistresponse", "target": "basemodel", "relation": "inherits", "confidence": "EXTRACTED", "source_file": "backend/app/api/knowledge_map.py", "source_location": "L134", "weight": 1.0}, {"source": "backend_app_api_knowledge_map_py", "target": "knowledge_map_meaningexampleresponse", "relation": "contains", "confidence": "EXTRACTED", "source_file": "backend/app/api/knowledge_map.py", "source_location": "L138", "weight": 1.0}, {"source": "knowledge_map_meaningexampleresponse", "target": "basemodel", "relation": "inherits", "confidence": "EXTRACTED", "source_file": "backend/app/api/knowledge_map.py", "source_location": "L138", "weight": 1.0}, {"source": "backend_app_api_knowledge_map_py", "target": "knowledge_map_learnervoiceassetresponse", "relation": "contains", "confidence": "EXTRACTED", "source_file": "backend/app/api/knowledge_map.py", "source_location": "L146", "weight": 1.0}, {"source": "knowledge_map_learnervoiceassetresponse", "target": "basemodel", "relation": "inherits", "confidence": "EXTRACTED", "source_file": "backend/app/api/knowledge_map.py", "source_location": "L146", "weight": 1.0}, {"source": "backend_app_api_knowledge_map_py", "target": "knowledge_map_translationresponse", "relation": "contains", "confidence": "EXTRACTED", "source_file": "backend/app/api/knowledge_map.py", "source_location": "L175", "weight": 1.0}, {"source": "knowledge_map_translationresponse", "target": "basemodel", "relation": "inherits", "confidence": "EXTRACTED", "source_file": "backend/app/api/knowledge_map.py", "source_location": "L175", "weight": 1.0}, {"source": "backend_app_api_knowledge_map_py", "target": "knowledge_map_relationresponse", "relation": "contains", "confidence": "EXTRACTED", "source_file": "backend/app/api/knowledge_map.py", "source_location": "L183", "weight": 1.0}, {"source": "knowledge_map_relationresponse", "target": "basemodel", "relation": "inherits", "confidence": "EXTRACTED", "source_file": "backend/app/api/knowledge_map.py", "source_location": "L183", "weight": 1.0}, {"source": "backend_app_api_knowledge_map_py", "target": "knowledge_map_relationgroupresponse", "relation": "contains", "confidence": "EXTRACTED", "source_file": "backend/app/api/knowledge_map.py", "source_location": "L189", "weight": 1.0}, {"source": "knowledge_map_relationgroupresponse", "target": "basemodel", "relation": "inherits", "confidence": "EXTRACTED", "source_file": "backend/app/api/knowledge_map.py", "source_location": "L189", "weight": 1.0}, {"source": "backend_app_api_knowledge_map_py", "target": "knowledge_map_confusablewordresponse", "relation": "contains", "confidence": "EXTRACTED", "source_file": "backend/app/api/knowledge_map.py", "source_location": "L194", "weight": 1.0}, {"source": "knowledge_map_confusablewordresponse", "target": "basemodel", "relation": "inherits", "confidence": "EXTRACTED", "source_file": "backend/app/api/knowledge_map.py", "source_location": "L194", "weight": 1.0}, {"source": "backend_app_api_knowledge_map_py", "target": "knowledge_map_inlinelinkedentryresponse", "relation": "contains", "confidence": "EXTRACTED", "source_file": "backend/app/api/knowledge_map.py", "source_location": "L200", "weight": 1.0}, {"source": "knowledge_map_inlinelinkedentryresponse", "target": "basemodel", "relation": "inherits", "confidence": "EXTRACTED", "source_file": "backend/app/api/knowledge_map.py", "source_location": "L200", "weight": 1.0}, {"source": "backend_app_api_knowledge_map_py", "target": "knowledge_map_linktargetresponse", "relation": "contains", "confidence": "EXTRACTED", "source_file": "backend/app/api/knowledge_map.py", "source_location": "L206", "weight": 1.0}, {"source": "knowledge_map_linktargetresponse", "target": "basemodel", "relation": "inherits", "confidence": "EXTRACTED", "source_file": "backend/app/api/knowledge_map.py", "source_location": "L206", "weight": 1.0}, {"source": "backend_app_api_knowledge_map_py", "target": "knowledge_map_linkedtextresponse", "relation": "contains", "confidence": "EXTRACTED", "source_file": "backend/app/api/knowledge_map.py", "source_location": "L212", "weight": 1.0}, {"source": "knowledge_map_linkedtextresponse", "target": "basemodel", "relation": "inherits", "confidence": "EXTRACTED", "source_file": "backend/app/api/knowledge_map.py", "source_location": "L212", "weight": 1.0}, {"source": "backend_app_api_knowledge_map_py", "target": "knowledge_map_wordformsresponse", "relation": "contains", "confidence": "EXTRACTED", "source_file": "backend/app/api/knowledge_map.py", "source_location": "L217", "weight": 1.0}, {"source": "knowledge_map_wordformsresponse", "target": "basemodel", "relation": "inherits", "confidence": "EXTRACTED", "source_file": "backend/app/api/knowledge_map.py", "source_location": "L217", "weight": 1.0}, {"source": "backend_app_api_knowledge_map_py", "target": "knowledge_map_knowledgemeaningresponse", "relation": "contains", "confidence": "EXTRACTED", "source_file": "backend/app/api/knowledge_map.py", "source_location": "L225", "weight": 1.0}, {"source": "knowledge_map_knowledgemeaningresponse", "target": "basemodel", "relation": "inherits", "confidence": "EXTRACTED", "source_file": "backend/app/api/knowledge_map.py", "source_location": "L225", "weight": 1.0}, {"source": "backend_app_api_knowledge_map_py", "target": "knowledge_map_phrasesenseresponse", "relation": "contains", "confidence": "EXTRACTED", "source_file": "backend/app/api/knowledge_map.py", "source_location": "L246", "weight": 1.0}, {"source": "knowledge_map_phrasesenseresponse", "target": "basemodel", "relation": "inherits", "confidence": "EXTRACTED", "source_file": "backend/app/api/knowledge_map.py", "source_location": "L246", "weight": 1.0}, {"source": "backend_app_api_knowledge_map_py", "target": "knowledge_map_adjacententryresponse", "relation": "contains", "confidence": "EXTRACTED", "source_file": "backend/app/api/knowledge_map.py", "source_location": "L265", "weight": 1.0}, {"source": "knowledge_map_adjacententryresponse", "target": "basemodel", "relation": "inherits", "confidence": "EXTRACTED", "source_file": "backend/app/api/knowledge_map.py", "source_location": "L265", "weight": 1.0}, {"source": "backend_app_api_knowledge_map_py", "target": "knowledge_map_reviewscheduleoptionresponse", "relation": "contains", "confidence": "EXTRACTED", "source_file": "backend/app/api/knowledge_map.py", "source_location": "L271", "weight": 1.0}, {"source": "knowledge_map_reviewscheduleoptionresponse", "target": "basemodel", "relation": "inherits", "confidence": "EXTRACTED", "source_file": "backend/app/api/knowledge_map.py", "source_location": "L271", "weight": 1.0}, {"source": "backend_app_api_knowledge_map_py", "target": "knowledge_map_entryreviewqueueresponse", "relation": "contains", "confidence": "EXTRACTED", "source_file": "backend/app/api/knowledge_map.py", "source_location": "L277", "weight": 1.0}, {"source": "knowledge_map_entryreviewqueueresponse", "target": "basemodel", "relation": "inherits", "confidence": "EXTRACTED", "source_file": "backend/app/api/knowledge_map.py", "source_location": "L277", "weight": 1.0}, {"source": "backend_app_api_knowledge_map_py", "target": "knowledge_map_serialize_model", "relation": "contains", "confidence": "EXTRACTED", "source_file": "backend/app/api/knowledge_map.py", "source_location": "L288", "weight": 1.0}, {"source": "backend_app_api_knowledge_map_py", "target": "knowledge_map_knowledgemapdetailresponse", "relation": "contains", "confidence": "EXTRACTED", "source_file": "backend/app/api/knowledge_map.py", "source_location": "L309", "weight": 1.0}, {"source": "knowledge_map_knowledgemapdetailresponse", "target": "basemodel", "relation": "inherits", "confidence": "EXTRACTED", "source_file": "backend/app/api/knowledge_map.py", "source_location": "L309", "weight": 1.0}, {"source": "backend_app_api_knowledge_map_py", "target": "knowledge_map_statusupdaterequest", "relation": "contains", "confidence": "EXTRACTED", "source_file": "backend/app/api/knowledge_map.py", "source_location": "L333", "weight": 1.0}, {"source": "knowledge_map_statusupdaterequest", "target": "basemodel", "relation": "inherits", "confidence": "EXTRACTED", "source_file": "backend/app/api/knowledge_map.py", "source_location": "L333", "weight": 1.0}, {"source": "backend_app_api_knowledge_map_py", "target": "knowledge_map_validate_status", "relation": "contains", "confidence": "EXTRACTED", "source_file": "backend/app/api/knowledge_map.py", "source_location": "L338", "weight": 1.0}, {"source": "backend_app_api_knowledge_map_py", "target": "knowledge_map_statusresponse", "relation": "contains", "confidence": "EXTRACTED", "source_file": "backend/app/api/knowledge_map.py", "source_location": "L344", "weight": 1.0}, {"source": "knowledge_map_statusresponse", "target": "basemodel", "relation": "inherits", "confidence": "EXTRACTED", "source_file": "backend/app/api/knowledge_map.py", "source_location": "L344", "weight": 1.0}, {"source": "backend_app_api_knowledge_map_py", "target": "knowledge_map_searchhistorywriterequest", "relation": "contains", "confidence": "EXTRACTED", "source_file": "backend/app/api/knowledge_map.py", "source_location": "L350", "weight": 1.0}, {"source": "knowledge_map_searchhistorywriterequest", "target": "basemodel", "relation": "inherits", "confidence": "EXTRACTED", "source_file": "backend/app/api/knowledge_map.py", "source_location": "L350", "weight": 1.0}, {"source": "backend_app_api_knowledge_map_py", "target": "knowledge_map_validate_query", "relation": "contains", "confidence": "EXTRACTED", "source_file": "backend/app/api/knowledge_map.py", "source_location": "L357", "weight": 1.0}, {"source": "backend_app_api_knowledge_map_py", "target": "knowledge_map_validate_entry_type", "relation": "contains", "confidence": "EXTRACTED", "source_file": "backend/app/api/knowledge_map.py", "source_location": "L365", "weight": 1.0}, {"source": "backend_app_api_knowledge_map_py", "target": "knowledge_map_searchhistoryitemresponse", "relation": "contains", "confidence": "EXTRACTED", "source_file": "backend/app/api/knowledge_map.py", "source_location": "L371", "weight": 1.0}, {"source": "knowledge_map_searchhistoryitemresponse", "target": "basemodel", "relation": "inherits", "confidence": "EXTRACTED", "source_file": "backend/app/api/knowledge_map.py", "source_location": "L371", "weight": 1.0}, {"source": "backend_app_api_knowledge_map_py", "target": "knowledge_map_searchhistorylistresponse", "relation": "contains", "confidence": "EXTRACTED", "source_file": "backend/app/api/knowledge_map.py", "source_location": "L378", "weight": 1.0}, {"source": "knowledge_map_searchhistorylistresponse", "target": "basemodel", "relation": "inherits", "confidence": "EXTRACTED", "source_file": "backend/app/api/knowledge_map.py", "source_location": "L378", "weight": 1.0}, {"source": "backend_app_api_knowledge_map_py", "target": "knowledge_map_summary_from_item", "relation": "contains", "confidence": "EXTRACTED", "source_file": "backend/app/api/knowledge_map.py", "source_location": "L382", "weight": 1.0}, {"source": "backend_app_api_knowledge_map_py", "target": "knowledge_map_voice_asset_response", "relation": "contains", "confidence": "EXTRACTED", "source_file": "backend/app/api/knowledge_map.py", "source_location": "L403", "weight": 1.0}, {"source": "backend_app_api_knowledge_map_py", "target": "knowledge_map_load_summary_voice_assets", "relation": "contains", "confidence": "EXTRACTED", "source_file": "backend/app/api/knowledge_map.py", "source_location": "L434", "weight": 1.0}, {"source": "backend_app_api_knowledge_map_py", "target": "knowledge_map_adjacent_entry", "relation": "contains", "confidence": "EXTRACTED", "source_file": "backend/app/api/knowledge_map.py", "source_location": "L470", "weight": 1.0}, {"source": "backend_app_api_knowledge_map_py", "target": "knowledge_map_dashboard_entry", "relation": "contains", "confidence": "EXTRACTED", "source_file": "backend/app/api/knowledge_map.py", "source_location": "L480", "weight": 1.0}, {"source": "backend_app_api_knowledge_map_py", "target": "knowledge_map_finalize_knowledge_map_metrics", "relation": "contains", "confidence": "EXTRACTED", "source_file": "backend/app/api/knowledge_map.py", "source_location": "L492", "weight": 1.0}, {"source": "backend_app_api_knowledge_map_py", "target": "knowledge_map_hydrate_summary_items", "relation": "contains", "confidence": "EXTRACTED", "source_file": "backend/app/api/knowledge_map.py", "source_location": "L517", "weight": 1.0}, {"source": "backend_app_api_knowledge_map_py", "target": "knowledge_map_get_knowledge_map_overview", "relation": "contains", "confidence": "EXTRACTED", "source_file": "backend/app/api/knowledge_map.py", "source_location": "L576", "weight": 1.0}, {"source": "backend_app_api_knowledge_map_py", "target": "knowledge_map_get_knowledge_map_dashboard", "relation": "contains", "confidence": "EXTRACTED", "source_file": "backend/app/api/knowledge_map.py", "source_location": "L595", "weight": 1.0}, {"source": "backend_app_api_knowledge_map_py", "target": "knowledge_map_get_knowledge_map_list", "relation": "contains", "confidence": "EXTRACTED", "source_file": "backend/app/api/knowledge_map.py", "source_location": "L621", "weight": 1.0}, {"source": "backend_app_api_knowledge_map_py", "target": "knowledge_map_get_knowledge_map_range", "relation": "contains", "confidence": "EXTRACTED", "source_file": "backend/app/api/knowledge_map.py", "source_location": "L666", "weight": 1.0}, {"source": "backend_app_api_knowledge_map_py", "target": "knowledge_map_get_knowledge_map_entry_detail", "relation": "contains", "confidence": "EXTRACTED", "source_file": "backend/app/api/knowledge_map.py", "source_location": "L698", "weight": 1.0}, {"source": "backend_app_api_knowledge_map_py", "target": "knowledge_map_put_knowledge_map_status", "relation": "contains", "confidence": "EXTRACTED", "source_file": "backend/app/api/knowledge_map.py", "source_location": "L1117", "weight": 1.0}, {"source": "backend_app_api_knowledge_map_py", "target": "knowledge_map_search_knowledge_map", "relation": "contains", "confidence": "EXTRACTED", "source_file": "backend/app/api/knowledge_map.py", "source_location": "L1165", "weight": 1.0}, {"source": "backend_app_api_knowledge_map_py", "target": "knowledge_map_get_search_history", "relation": "contains", "confidence": "EXTRACTED", "source_file": "backend/app/api/knowledge_map.py", "source_location": "L1186", "weight": 1.0}, {"source": "backend_app_api_knowledge_map_py", "target": "knowledge_map_post_search_history", "relation": "contains", "confidence": "EXTRACTED", "source_file": "backend/app/api/knowledge_map.py", "source_location": "L1215", "weight": 1.0}, {"source": "knowledge_map_summary_from_item", "target": "knowledge_map_knowledgemapentrysummary", "relation": "calls", "confidence": "EXTRACTED", "source_file": "backend/app/api/knowledge_map.py", "source_location": "L383", "weight": 1.0}, {"source": "knowledge_map_voice_asset_response", "target": "knowledge_map_learnervoiceassetresponse", "relation": "calls", "confidence": "EXTRACTED", "source_file": "backend/app/api/knowledge_map.py", "source_location": "L404", "weight": 1.0}, {"source": "knowledge_map_load_summary_voice_assets", "target": "knowledge_map_voice_asset_response", "relation": "calls", "confidence": "EXTRACTED", "source_file": "backend/app/api/knowledge_map.py", "source_location": "L466", "weight": 1.0}, {"source": "knowledge_map_adjacent_entry", "target": "knowledge_map_adjacententryresponse", "relation": "calls", "confidence": "EXTRACTED", "source_file": "backend/app/api/knowledge_map.py", "source_location": "L473", "weight": 1.0}, {"source": "knowledge_map_dashboard_entry", "target": "knowledge_map_knowledgemapadjacententryresponse", "relation": "calls", "confidence": "EXTRACTED", "source_file": "backend/app/api/knowledge_map.py", "source_location": "L483", "weight": 1.0}, {"source": "knowledge_map_hydrate_summary_items", "target": "knowledge_map_load_summary_voice_assets", "relation": "calls", "confidence": "EXTRACTED", "source_file": "backend/app/api/knowledge_map.py", "source_location": "L527", "weight": 1.0}, {"source": "knowledge_map_get_knowledge_map_overview", "target": "knowledge_map_finalize_knowledge_map_metrics", "relation": "calls", "confidence": "EXTRACTED", "source_file": "backend/app/api/knowledge_map.py", "source_location": "L584", "weight": 1.0}, {"source": "knowledge_map_get_knowledge_map_overview", "target": "knowledge_map_knowledgemapoverviewresponse", "relation": "calls", "confidence": "EXTRACTED", "source_file": "backend/app/api/knowledge_map.py", "source_location": "L591", "weight": 1.0}, {"source": "knowledge_map_get_knowledge_map_dashboard", "target": "knowledge_map_finalize_knowledge_map_metrics", "relation": "calls", "confidence": "EXTRACTED", "source_file": "backend/app/api/knowledge_map.py", "source_location": "L603", "weight": 1.0}, {"source": "knowledge_map_get_knowledge_map_dashboard", "target": "knowledge_map_knowledgemapdashboardresponse", "relation": "calls", "confidence": "EXTRACTED", "source_file": "backend/app/api/knowledge_map.py", "source_location": "L610", "weight": 1.0}, {"source": "knowledge_map_get_knowledge_map_dashboard", "target": "knowledge_map_rangecountsresponse", "relation": "calls", "confidence": "EXTRACTED", "source_file": "backend/app/api/knowledge_map.py", "source_location": "L612", "weight": 1.0}, {"source": "knowledge_map_get_knowledge_map_dashboard", "target": "knowledge_map_dashboard_entry", "relation": "calls", "confidence": "EXTRACTED", "source_file": "backend/app/api/knowledge_map.py", "source_location": "L615", "weight": 1.0}, {"source": "knowledge_map_get_knowledge_map_list", "target": "knowledge_map_hydrate_summary_items", "relation": "calls", "confidence": "EXTRACTED", "source_file": "backend/app/api/knowledge_map.py", "source_location": "L654", "weight": 1.0}, {"source": "knowledge_map_get_knowledge_map_list", "target": "knowledge_map_finalize_knowledge_map_metrics", "relation": "calls", "confidence": "EXTRACTED", "source_file": "backend/app/api/knowledge_map.py", "source_location": "L655", "weight": 1.0}, {"source": "knowledge_map_get_knowledge_map_list", "target": "knowledge_map_knowledgemaplistresponse", "relation": "calls", "confidence": "EXTRACTED", "source_file": "backend/app/api/knowledge_map.py", "source_location": "L662", "weight": 1.0}, {"source": "knowledge_map_get_knowledge_map_list", "target": "knowledge_map_summary_from_item", "relation": "calls", "confidence": "EXTRACTED", "source_file": "backend/app/api/knowledge_map.py", "source_location": "L662", "weight": 1.0}, {"source": "knowledge_map_get_knowledge_map_range", "target": "knowledge_map_hydrate_summary_items", "relation": "calls", "confidence": "EXTRACTED", "source_file": "backend/app/api/knowledge_map.py", "source_location": "L675", "weight": 1.0}, {"source": "knowledge_map_get_knowledge_map_range", "target": "knowledge_map_finalize_knowledge_map_metrics", "relation": "calls", "confidence": "EXTRACTED", "source_file": "backend/app/api/knowledge_map.py", "source_location": "L680", "weight": 1.0}, {"source": "knowledge_map_get_knowledge_map_range", "target": "knowledge_map_knowledgemaprangeresponse", "relation": "calls", "confidence": "EXTRACTED", "source_file": "backend/app/api/knowledge_map.py", "source_location": "L688", "weight": 1.0}, {"source": "knowledge_map_get_knowledge_map_range", "target": "knowledge_map_summary_from_item", "relation": "calls", "confidence": "EXTRACTED", "source_file": "backend/app/api/knowledge_map.py", "source_location": "L693", "weight": 1.0}, {"source": "knowledge_map_get_knowledge_map_entry_detail", "target": "knowledge_map_knowledgemapdetailresponse", "relation": "calls", "confidence": "EXTRACTED", "source_file": "backend/app/api/knowledge_map.py", "source_location": "L781", "weight": 1.0}, {"source": "knowledge_map_get_knowledge_map_entry_detail", "target": "knowledge_map_voice_asset_response", "relation": "calls", "confidence": "EXTRACTED", "source_file": "backend/app/api/knowledge_map.py", "source_location": "L793", "weight": 1.0}, {"source": "knowledge_map_get_knowledge_map_entry_detail", "target": "knowledge_map_wordformsresponse", "relation": "calls", "confidence": "EXTRACTED", "source_file": "backend/app/api/knowledge_map.py", "source_location": "L795", "weight": 1.0}, {"source": "knowledge_map_get_knowledge_map_entry_detail", "target": "knowledge_map_linkedtextresponse", "relation": "calls", "confidence": "EXTRACTED", "source_file": "backend/app/api/knowledge_map.py", "source_location": "L799", "weight": 1.0}, {"source": "knowledge_map_get_knowledge_map_entry_detail", "target": "knowledge_map_linktargetresponse", "relation": "calls", "confidence": "EXTRACTED", "source_file": "backend/app/api/knowledge_map.py", "source_location": "L801", "weight": 1.0}, {"source": "knowledge_map_get_knowledge_map_entry_detail", "target": "knowledge_map_knowledgemeaningresponse", "relation": "calls", "confidence": "EXTRACTED", "source_file": "backend/app/api/knowledge_map.py", "source_location": "L809", "weight": 1.0}, {"source": "knowledge_map_get_knowledge_map_entry_detail", "target": "knowledge_map_meaningexampleresponse", "relation": "calls", "confidence": "EXTRACTED", "source_file": "backend/app/api/knowledge_map.py", "source_location": "L847", "weight": 1.0}, {"source": "knowledge_map_get_knowledge_map_entry_detail", "target": "knowledge_map_inlinelinkedentryresponse", "relation": "calls", "confidence": "EXTRACTED", "source_file": "backend/app/api/knowledge_map.py", "source_location": "L862", "weight": 1.0}, {"source": "knowledge_map_get_knowledge_map_entry_detail", "target": "knowledge_map_translationresponse", "relation": "calls", "confidence": "EXTRACTED", "source_file": "backend/app/api/knowledge_map.py", "source_location": "L872", "weight": 1.0}, {"source": "knowledge_map_get_knowledge_map_entry_detail", "target": "knowledge_map_relationresponse", "relation": "calls", "confidence": "EXTRACTED", "source_file": "backend/app/api/knowledge_map.py", "source_location": "L882", "weight": 1.0}, {"source": "knowledge_map_get_knowledge_map_entry_detail", "target": "knowledge_map_relationgroupresponse", "relation": "calls", "confidence": "EXTRACTED", "source_file": "backend/app/api/knowledge_map.py", "source_location": "L893", "weight": 1.0}, {"source": "knowledge_map_get_knowledge_map_entry_detail", "target": "knowledge_map_confusablewordresponse", "relation": "calls", "confidence": "EXTRACTED", "source_file": "backend/app/api/knowledge_map.py", "source_location": "L900", "weight": 1.0}, {"source": "knowledge_map_get_knowledge_map_entry_detail", "target": "knowledge_map_entryreviewqueueresponse", "relation": "calls", "confidence": "EXTRACTED", "source_file": "backend/app/api/knowledge_map.py", "source_location": "L912", "weight": 1.0}, {"source": "knowledge_map_get_knowledge_map_entry_detail", "target": "knowledge_map_reviewscheduleoptionresponse", "relation": "calls", "confidence": "EXTRACTED", "source_file": "backend/app/api/knowledge_map.py", "source_location": "L921", "weight": 1.0}, {"source": "knowledge_map_get_knowledge_map_entry_detail", "target": "knowledge_map_adjacent_entry", "relation": "calls", "confidence": "EXTRACTED", "source_file": "backend/app/api/knowledge_map.py", "source_location": "L928", "weight": 1.0}, {"source": "knowledge_map_get_knowledge_map_entry_detail", "target": "knowledge_map_finalize_knowledge_map_metrics", "relation": "calls", "confidence": "EXTRACTED", "source_file": "backend/app/api/knowledge_map.py", "source_location": "L931", "weight": 1.0}, {"source": "knowledge_map_get_knowledge_map_entry_detail", "target": "knowledge_map_phrasesenseresponse", "relation": "calls", "confidence": "EXTRACTED", "source_file": "backend/app/api/knowledge_map.py", "source_location": "L988", "weight": 1.0}, {"source": "knowledge_map_put_knowledge_map_status", "target": "knowledge_map_finalize_knowledge_map_metrics", "relation": "calls", "confidence": "EXTRACTED", "source_file": "backend/app/api/knowledge_map.py", "source_location": "L1154", "weight": 1.0}, {"source": "knowledge_map_put_knowledge_map_status", "target": "knowledge_map_statusresponse", "relation": "calls", "confidence": "EXTRACTED", "source_file": "backend/app/api/knowledge_map.py", "source_location": "L1161", "weight": 1.0}, {"source": "knowledge_map_search_knowledge_map", "target": "knowledge_map_hydrate_summary_items", "relation": "calls", "confidence": "EXTRACTED", "source_file": "backend/app/api/knowledge_map.py", "source_location": "L1174", "weight": 1.0}, {"source": "knowledge_map_search_knowledge_map", "target": "knowledge_map_finalize_knowledge_map_metrics", "relation": "calls", "confidence": "EXTRACTED", "source_file": "backend/app/api/knowledge_map.py", "source_location": "L1175", "weight": 1.0}, {"source": "knowledge_map_search_knowledge_map", "target": "knowledge_map_knowledgemapsearchresponse", "relation": "calls", "confidence": "EXTRACTED", "source_file": "backend/app/api/knowledge_map.py", "source_location": "L1182", "weight": 1.0}, {"source": "knowledge_map_search_knowledge_map", "target": "knowledge_map_summary_from_item", "relation": "calls", "confidence": "EXTRACTED", "source_file": "backend/app/api/knowledge_map.py", "source_location": "L1182", "weight": 1.0}, {"source": "knowledge_map_get_search_history", "target": "knowledge_map_finalize_knowledge_map_metrics", "relation": "calls", "confidence": "EXTRACTED", "source_file": "backend/app/api/knowledge_map.py", "source_location": "L1194", "weight": 1.0}, {"source": "knowledge_map_get_search_history", "target": "knowledge_map_searchhistorylistresponse", "relation": "calls", "confidence": "EXTRACTED", "source_file": "backend/app/api/knowledge_map.py", "source_location": "L1201", "weight": 1.0}, {"source": "knowledge_map_get_search_history", "target": "knowledge_map_searchhistoryitemresponse", "relation": "calls", "confidence": "EXTRACTED", "source_file": "backend/app/api/knowledge_map.py", "source_location": "L1203", "weight": 1.0}, {"source": "knowledge_map_post_search_history", "target": "knowledge_map_finalize_knowledge_map_metrics", "relation": "calls", "confidence": "EXTRACTED", "source_file": "backend/app/api/knowledge_map.py", "source_location": "L1242", "weight": 1.0}, {"source": "knowledge_map_post_search_history", "target": "knowledge_map_searchhistoryitemresponse", "relation": "calls", "confidence": "EXTRACTED", "source_file": "backend/app/api/knowledge_map.py", "source_location": "L1249", "weight": 1.0}], "raw_calls": [{"caller_nid": "knowledge_map_validate_status", "callee": "ValueError", "source_file": "backend/app/api/knowledge_map.py", "source_location": "L340"}, {"caller_nid": "knowledge_map_validate_query", "callee": "strip", "source_file": "backend/app/api/knowledge_map.py", "source_location": "L358"}, {"caller_nid": "knowledge_map_validate_query", "callee": "ValueError", "source_file": "backend/app/api/knowledge_map.py", "source_location": "L360"}, {"caller_nid": "knowledge_map_validate_entry_type", "callee": "ValueError", "source_file": "backend/app/api/knowledge_map.py", "source_location": "L367"}, {"caller_nid": "knowledge_map_summary_from_item", "callee": "str", "source_file": "backend/app/api/knowledge_map.py", "source_location": "L385"}, {"caller_nid": "knowledge_map_summary_from_item", "callee": "get", "source_file": "backend/app/api/knowledge_map.py", "source_location": "L392"}, {"caller_nid": "knowledge_map_summary_from_item", "callee": "get", "source_file": "backend/app/api/knowledge_map.py", "source_location": "L395"}, {"caller_nid": "knowledge_map_summary_from_item", "callee": "get", "source_file": "backend/app/api/knowledge_map.py", "source_location": "L396"}, {"caller_nid": "knowledge_map_summary_from_item", "callee": "get", "source_file": "backend/app/api/knowledge_map.py", "source_location": "L399"}, {"caller_nid": "knowledge_map_voice_asset_response", "callee": "str", "source_file": "backend/app/api/knowledge_map.py", "source_location": "L405"}, {"caller_nid": "knowledge_map_voice_asset_response", "callee": "str", "source_file": "backend/app/api/knowledge_map.py", "source_location": "L407"}, {"caller_nid": "knowledge_map_voice_asset_response", "callee": "str", "source_file": "backend/app/api/knowledge_map.py", "source_location": "L408"}, {"caller_nid": "knowledge_map_voice_asset_response", "callee": "str", "source_file": "backend/app/api/knowledge_map.py", "source_location": "L409"}, {"caller_nid": "knowledge_map_voice_asset_response", "callee": "str", "source_file": "backend/app/api/knowledge_map.py", "source_location": "L410"}, {"caller_nid": "knowledge_map_voice_asset_response", "callee": "int", "source_file": "backend/app/api/knowledge_map.py", "source_location": "L421"}, {"caller_nid": "knowledge_map_voice_asset_response", "callee": "int", "source_file": "backend/app/api/knowledge_map.py", "source_location": "L422"}, {"caller_nid": "knowledge_map_voice_asset_response", "callee": "build_voice_asset_playback_url", "source_file": "backend/app/api/knowledge_map.py", "source_location": "L424"}, {"caller_nid": "knowledge_map_voice_asset_response", "callee": "isoformat", "source_file": "backend/app/api/knowledge_map.py", "source_location": "L430"}, {"caller_nid": "knowledge_map_load_summary_voice_assets", "callee": "append", "source_file": "backend/app/api/knowledge_map.py", "source_location": "L442"}, {"caller_nid": "knowledge_map_load_summary_voice_assets", "callee": "in_", "source_file": "backend/app/api/knowledge_map.py", "source_location": "L443"}, {"caller_nid": "knowledge_map_load_summary_voice_assets", "callee": "append", "source_file": "backend/app/api/knowledge_map.py", "source_location": "L446"}, {"caller_nid": "knowledge_map_load_summary_voice_assets", "callee": "in_", "source_file": "backend/app/api/knowledge_map.py", "source_location": "L447"}, {"caller_nid": "knowledge_map_load_summary_voice_assets", "callee": "execute", "source_file": "backend/app/api/knowledge_map.py", "source_location": "L453"}, {"caller_nid": "knowledge_map_load_summary_voice_assets", "callee": "where", "source_file": "backend/app/api/knowledge_map.py", "source_location": "L454"}, {"caller_nid": "knowledge_map_load_summary_voice_assets", "callee": "options", "source_file": "backend/app/api/knowledge_map.py", "source_location": "L454"}, {"caller_nid": "knowledge_map_load_summary_voice_assets", "callee": "select", "source_file": "backend/app/api/knowledge_map.py", "source_location": "L454"}, {"caller_nid": "knowledge_map_load_summary_voice_assets", "callee": "selectinload", "source_file": "backend/app/api/knowledge_map.py", "source_location": "L455"}, {"caller_nid": "knowledge_map_load_summary_voice_assets", "callee": "or_", "source_file": "backend/app/api/knowledge_map.py", "source_location": "L456"}, {"caller_nid": "knowledge_map_load_summary_voice_assets", "callee": "all", "source_file": "backend/app/api/knowledge_map.py", "source_location": "L459"}, {"caller_nid": "knowledge_map_load_summary_voice_assets", "callee": "scalars", "source_file": "backend/app/api/knowledge_map.py", "source_location": "L459"}, {"caller_nid": "knowledge_map_load_summary_voice_assets", "callee": "append", "source_file": "backend/app/api/knowledge_map.py", "source_location": "L466"}, {"caller_nid": "knowledge_map_load_summary_voice_assets", "callee": "setdefault", "source_file": "backend/app/api/knowledge_map.py", "source_location": "L466"}, {"caller_nid": "knowledge_map_adjacent_entry", "callee": "str", "source_file": "backend/app/api/knowledge_map.py", "source_location": "L475"}, {"caller_nid": "knowledge_map_dashboard_entry", "callee": "str", "source_file": "backend/app/api/knowledge_map.py", "source_location": "L485"}, {"caller_nid": "knowledge_map_finalize_knowledge_map_metrics", "callee": "finalize_request_db_metrics", "source_file": "backend/app/api/knowledge_map.py", "source_location": "L500"}, {"caller_nid": "knowledge_map_finalize_knowledge_map_metrics", "callee": "info", "source_file": "backend/app/api/knowledge_map.py", "source_location": "L506"}, {"caller_nid": "knowledge_map_hydrate_summary_items", "callee": "get_preferences", "source_file": "backend/app/api/knowledge_map.py", "source_location": "L529"}, {"caller_nid": "knowledge_map_hydrate_summary_items", "callee": "load_word_summary_map", "source_file": "backend/app/api/knowledge_map.py", "source_location": "L531"}, {"caller_nid": "knowledge_map_hydrate_summary_items", "callee": "execute", "source_file": "backend/app/api/knowledge_map.py", "source_location": "L532"}, {"caller_nid": "knowledge_map_hydrate_summary_items", "callee": "where", "source_file": "backend/app/api/knowledge_map.py", "source_location": "L532"}, {"caller_nid": "knowledge_map_hydrate_summary_items", "callee": "select", "source_file": "backend/app/api/knowledge_map.py", "source_location": "L532"}, {"caller_nid": "knowledge_map_hydrate_summary_items", "callee": "in_", "source_file": "backend/app/api/knowledge_map.py", "source_location": "L532"}, {"caller_nid": "knowledge_map_hydrate_summary_items", "callee": "all", "source_file": "backend/app/api/knowledge_map.py", "source_location": "L533"}, {"caller_nid": "knowledge_map_hydrate_summary_items", "callee": "scalars", "source_file": "backend/app/api/knowledge_map.py", "source_location": "L533"}, {"caller_nid": "knowledge_map_hydrate_summary_items", "callee": "get", "source_file": "backend/app/api/knowledge_map.py", "source_location": "L538"}, {"caller_nid": "knowledge_map_hydrate_summary_items", "callee": "get", "source_file": "backend/app/api/knowledge_map.py", "source_location": "L539"}, {"caller_nid": "knowledge_map_hydrate_summary_items", "callee": "get", "source_file": "backend/app/api/knowledge_map.py", "source_location": "L540"}, {"caller_nid": "knowledge_map_hydrate_summary_items", "callee": "get", "source_file": "backend/app/api/knowledge_map.py", "source_location": "L540"}, {"caller_nid": "knowledge_map_hydrate_summary_items", "callee": "get", "source_file": "backend/app/api/knowledge_map.py", "source_location": "L541"}, {"caller_nid": "knowledge_map_hydrate_summary_items", "callee": "get", "source_file": "backend/app/api/knowledge_map.py", "source_location": "L541"}, {"caller_nid": "knowledge_map_hydrate_summary_items", "callee": "get", "source_file": "backend/app/api/knowledge_map.py", "source_location": "L542"}, {"caller_nid": "knowledge_map_hydrate_summary_items", "callee": "get", "source_file": "backend/app/api/knowledge_map.py", "source_location": "L543"}, {"caller_nid": "knowledge_map_hydrate_summary_items", "callee": "select_pronunciation", "source_file": "backend/app/api/knowledge_map.py", "source_location": "L545"}, {"caller_nid": "knowledge_map_hydrate_summary_items", "callee": "get", "source_file": "backend/app/api/knowledge_map.py", "source_location": "L547"}, {"caller_nid": "knowledge_map_hydrate_summary_items", "callee": "extract_pronunciations", "source_file": "backend/app/api/knowledge_map.py", "source_location": "L549"}, {"caller_nid": "knowledge_map_hydrate_summary_items", "callee": "model_dump", "source_file": "backend/app/api/knowledge_map.py", "source_location": "L551"}, {"caller_nid": "knowledge_map_hydrate_summary_items", "callee": "get", "source_file": "backend/app/api/knowledge_map.py", "source_location": "L552"}, {"caller_nid": "knowledge_map_hydrate_summary_items", "callee": "load_phrase_summary_map", "source_file": "backend/app/api/knowledge_map.py", "source_location": "L556"}, {"caller_nid": "knowledge_map_hydrate_summary_items", "callee": "get", "source_file": "backend/app/api/knowledge_map.py", "source_location": "L560"}, {"caller_nid": "knowledge_map_hydrate_summary_items", "callee": "get", "source_file": "backend/app/api/knowledge_map.py", "source_location": "L565"}, {"caller_nid": "knowledge_map_hydrate_summary_items", "callee": "get", "source_file": "backend/app/api/knowledge_map.py", "source_location": "L566"}, {"caller_nid": "knowledge_map_hydrate_summary_items", "callee": "model_dump", "source_file": "backend/app/api/knowledge_map.py", "source_location": "L568"}, {"caller_nid": "knowledge_map_hydrate_summary_items", "callee": "get", "source_file": "backend/app/api/knowledge_map.py", "source_location": "L569"}, {"caller_nid": "knowledge_map_get_knowledge_map_overview", "callee": "perf_counter", "source_file": "backend/app/api/knowledge_map.py", "source_location": "L582"}, {"caller_nid": "knowledge_map_get_knowledge_map_overview", "callee": "load_overview_summary", "source_file": "backend/app/api/knowledge_map.py", "source_location": "L583"}, {"caller_nid": "knowledge_map_get_knowledge_map_overview", "callee": "len", "source_file": "backend/app/api/knowledge_map.py", "source_location": "L589"}, {"caller_nid": "knowledge_map_get_knowledge_map_dashboard", "callee": "perf_counter", "source_file": "backend/app/api/knowledge_map.py", "source_location": "L601"}, {"caller_nid": "knowledge_map_get_knowledge_map_dashboard", "callee": "load_dashboard_summary", "source_file": "backend/app/api/knowledge_map.py", "source_location": "L602"}, {"caller_nid": "knowledge_map_get_knowledge_map_list", "callee": "HTTPException", "source_file": "backend/app/api/knowledge_map.py", "source_location": "L633"}, {"caller_nid": "knowledge_map_get_knowledge_map_list", "callee": "HTTPException", "source_file": "backend/app/api/knowledge_map.py", "source_location": "L635"}, {"caller_nid": "knowledge_map_get_knowledge_map_list", "callee": "HTTPException", "source_file": "backend/app/api/knowledge_map.py", "source_location": "L637"}, {"caller_nid": "knowledge_map_get_knowledge_map_list", "callee": "perf_counter", "source_file": "backend/app/api/knowledge_map.py", "source_location": "L645"}, {"caller_nid": "knowledge_map_get_knowledge_map_list", "callee": "build_catalog", "source_file": "backend/app/api/knowledge_map.py", "source_location": "L646"}, {"caller_nid": "knowledge_map_get_knowledge_map_list", "callee": "len", "source_file": "backend/app/api/knowledge_map.py", "source_location": "L660"}, {"caller_nid": "knowledge_map_get_knowledge_map_range", "callee": "perf_counter", "source_file": "backend/app/api/knowledge_map.py", "source_location": "L673"}, {"caller_nid": "knowledge_map_get_knowledge_map_range", "callee": "load_range_catalog_items", "source_file": "backend/app/api/knowledge_map.py", "source_location": "L674"}, {"caller_nid": "knowledge_map_get_knowledge_map_range", "callee": "len", "source_file": "backend/app/api/knowledge_map.py", "source_location": "L685"}, {"caller_nid": "knowledge_map_get_knowledge_map_entry_detail", "callee": "HTTPException", "source_file": "backend/app/api/knowledge_map.py", "source_location": "L707"}, {"caller_nid": "knowledge_map_get_knowledge_map_entry_detail", "callee": "perf_counter", "source_file": "backend/app/api/knowledge_map.py", "source_location": "L709"}, {"caller_nid": "knowledge_map_get_knowledge_map_entry_detail", "callee": "get_preferences", "source_file": "backend/app/api/knowledge_map.py", "source_location": "L710"}, {"caller_nid": "knowledge_map_get_knowledge_map_entry_detail", "callee": "execute", "source_file": "backend/app/api/knowledge_map.py", "source_location": "L713"}, {"caller_nid": "knowledge_map_get_knowledge_map_entry_detail", "callee": "where", "source_file": "backend/app/api/knowledge_map.py", "source_location": "L714"}, {"caller_nid": "knowledge_map_get_knowledge_map_entry_detail", "callee": "options", "source_file": "backend/app/api/knowledge_map.py", "source_location": "L714"}, {"caller_nid": "knowledge_map_get_knowledge_map_entry_detail", "callee": "select", "source_file": "backend/app/api/knowledge_map.py", "source_location": "L714"}, {"caller_nid": "knowledge_map_get_knowledge_map_entry_detail", "callee": "load_only", "source_file": "backend/app/api/knowledge_map.py", "source_location": "L716"}, {"caller_nid": "knowledge_map_get_knowledge_map_entry_detail", "callee": "selectinload", "source_file": "backend/app/api/knowledge_map.py", "source_location": "L725"}, {"caller_nid": "knowledge_map_get_knowledge_map_entry_detail", "callee": "selectinload", "source_file": "backend/app/api/knowledge_map.py", "source_location": "L726"}, {"caller_nid": "knowledge_map_get_knowledge_map_entry_detail", "callee": "selectinload", "source_file": "backend/app/api/knowledge_map.py", "source_location": "L727"}, {"caller_nid": "knowledge_map_get_knowledge_map_entry_detail", "callee": "scalar_one_or_none", "source_file": "backend/app/api/knowledge_map.py", "source_location": "L731"}, {"caller_nid": "knowledge_map_get_knowledge_map_entry_detail", "callee": "HTTPException", "source_file": "backend/app/api/knowledge_map.py", "source_location": "L733"}, {"caller_nid": "knowledge_map_get_knowledge_map_entry_detail", "callee": "execute", "source_file": "backend/app/api/knowledge_map.py", "source_location": "L735"}, {"caller_nid": "knowledge_map_get_knowledge_map_entry_detail", "callee": "order_by", "source_file": "backend/app/api/knowledge_map.py", "source_location": "L736"}, {"caller_nid": "knowledge_map_get_knowledge_map_entry_detail", "callee": "where", "source_file": "backend/app/api/knowledge_map.py", "source_location": "L736"}, {"caller_nid": "knowledge_map_get_knowledge_map_entry_detail", "callee": "options", "source_file": "backend/app/api/knowledge_map.py", "source_location": "L736"}, {"caller_nid": "knowledge_map_get_knowledge_map_entry_detail", "callee": "select", "source_file": "backend/app/api/knowledge_map.py", "source_location": "L736"}, {"caller_nid": "knowledge_map_get_knowledge_map_entry_detail", "callee": "selectinload", "source_file": "backend/app/api/knowledge_map.py", "source_location": "L737"}, {"caller_nid": "knowledge_map_get_knowledge_map_entry_detail", "callee": "asc", "source_file": "backend/app/api/knowledge_map.py", "source_location": "L739"}, {"caller_nid": "knowledge_map_get_knowledge_map_entry_detail", "callee": "all", "source_file": "backend/app/api/knowledge_map.py", "source_location": "L741"}, {"caller_nid": "knowledge_map_get_knowledge_map_entry_detail", "callee": "scalars", "source_file": "backend/app/api/knowledge_map.py", "source_location": "L741"}, {"caller_nid": "knowledge_map_get_knowledge_map_entry_detail", "callee": "load_word_detail_relations", "source_file": "backend/app/api/knowledge_map.py", "source_location": "L743"}, {"caller_nid": "knowledge_map_get_knowledge_map_entry_detail", "callee": "values", "source_file": "backend/app/api/knowledge_map.py", "source_location": "L744"}, {"caller_nid": "knowledge_map_get_knowledge_map_entry_detail", "callee": "load_word_voice_assets", "source_file": "backend/app/api/knowledge_map.py", "source_location": "L745"}, {"caller_nid": "knowledge_map_get_knowledge_map_entry_detail", "callee": "get_status_row", "source_file": "backend/app/api/knowledge_map.py", "source_location": "L751"}, {"caller_nid": "knowledge_map_get_knowledge_map_entry_detail", "callee": "load_catalog_neighbors", "source_file": "backend/app/api/knowledge_map.py", "source_location": "L752"}, {"caller_nid": "knowledge_map_get_knowledge_map_entry_detail", "callee": "normalize_word_forms", "source_file": "backend/app/api/knowledge_map.py", "source_location": "L753"}, {"caller_nid": "knowledge_map_get_knowledge_map_entry_detail", "callee": "collect_exact_lookup_terms", "source_file": "backend/app/api/knowledge_map.py", "source_location": "L755"}, {"caller_nid": "knowledge_map_get_knowledge_map_entry_detail", "callee": "values", "source_file": "backend/app/api/knowledge_map.py", "source_location": "L758"}, {"caller_nid": "knowledge_map_get_knowledge_map_entry_detail", "callee": "normalize_confusable_words", "source_file": "backend/app/api/knowledge_map.py", "source_location": "L759"}, {"caller_nid": "knowledge_map_get_knowledge_map_entry_detail", "callee": "values", "source_file": "backend/app/api/knowledge_map.py", "source_location": "L761"}, {"caller_nid": "knowledge_map_get_knowledge_map_entry_detail", "callee": "load_entry_lookup_for_terms", "source_file": "backend/app/api/knowledge_map.py", "source_location": "L763"}, {"caller_nid": "knowledge_map_get_knowledge_map_entry_detail", "callee": "build_word_translation_map", "source_file": "backend/app/api/knowledge_map.py", "source_location": "L766"}, {"caller_nid": "knowledge_map_get_knowledge_map_entry_detail", "callee": "values", "source_file": "backend/app/api/knowledge_map.py", "source_location": "L767"}, {"caller_nid": "knowledge_map_get_knowledge_map_entry_detail", "callee": "get_entry_queue_schedule", "source_file": "backend/app/api/knowledge_map.py", "source_location": "L776"}, {"caller_nid": "knowledge_map_get_knowledge_map_entry_detail", "callee": "ReviewService", "source_file": "backend/app/api/knowledge_map.py", "source_location": "L776"}, {"caller_nid": "knowledge_map_get_knowledge_map_entry_detail", "callee": "str", "source_file": "backend/app/api/knowledge_map.py", "source_location": "L783"}, {"caller_nid": "knowledge_map_get_knowledge_map_entry_detail", "callee": "int", "source_file": "backend/app/api/knowledge_map.py", "source_location": "L786"}, {"caller_nid": "knowledge_map_get_knowledge_map_entry_detail", "callee": "select_pronunciation", "source_file": "backend/app/api/knowledge_map.py", "source_location": "L789"}, {"caller_nid": "knowledge_map_get_knowledge_map_entry_detail", "callee": "list", "source_file": "backend/app/api/knowledge_map.py", "source_location": "L792"}, {"caller_nid": "knowledge_map_get_knowledge_map_entry_detail", "callee": "extract_pronunciations", "source_file": "backend/app/api/knowledge_map.py", "source_location": "L794"}, {"caller_nid": "knowledge_map_get_knowledge_map_entry_detail", "callee": "resolve_exact_match_target", "source_file": "backend/app/api/knowledge_map.py", "source_location": "L801"}, {"caller_nid": "knowledge_map_get_knowledge_map_entry_detail", "callee": "str", "source_file": "backend/app/api/knowledge_map.py", "source_location": "L810"}, {"caller_nid": "knowledge_map_get_knowledge_map_entry_detail", "callee": "next", "source_file": "backend/app/api/knowledge_map.py", "source_location": "L812"}, {"caller_nid": "knowledge_map_get_knowledge_map_entry_detail", "callee": "get", "source_file": "backend/app/api/knowledge_map.py", "source_location": "L815"}, {"caller_nid": "knowledge_map_get_knowledge_map_entry_detail", "callee": "next", "source_file": "backend/app/api/knowledge_map.py", "source_location": "L822"}, {"caller_nid": "knowledge_map_get_knowledge_map_entry_detail", "callee": "getattr", "source_file": "backend/app/api/knowledge_map.py", "source_location": "L824"}, {"caller_nid": "knowledge_map_get_knowledge_map_entry_detail", "callee": "get", "source_file": "backend/app/api/knowledge_map.py", "source_location": "L825"}, {"caller_nid": "knowledge_map_get_knowledge_map_entry_detail", "callee": "normalize_meaning_metadata", "source_file": "backend/app/api/knowledge_map.py", "source_location": "L832"}, {"caller_nid": "knowledge_map_get_knowledge_map_entry_detail", "callee": "normalize_meaning_metadata", "source_file": "backend/app/api/knowledge_map.py", "source_location": "L833"}, {"caller_nid": "knowledge_map_get_knowledge_map_entry_detail", "callee": "relation_terms", "source_file": "backend/app/api/knowledge_map.py", "source_location": "L836"}, {"caller_nid": "knowledge_map_get_knowledge_map_entry_detail", "callee": "get", "source_file": "backend/app/api/knowledge_map.py", "source_location": "L836"}, {"caller_nid": "knowledge_map_get_knowledge_map_entry_detail", "callee": "relation_terms", "source_file": "backend/app/api/knowledge_map.py", "source_location": "L840"}, {"caller_nid": "knowledge_map_get_knowledge_map_entry_detail", "callee": "get", "source_file": "backend/app/api/knowledge_map.py", "source_location": "L840"}, {"caller_nid": "knowledge_map_get_knowledge_map_entry_detail", "callee": "relation_terms", "source_file": "backend/app/api/knowledge_map.py", "source_location": "L844"}, {"caller_nid": "knowledge_map_get_knowledge_map_entry_detail", "callee": "get", "source_file": "backend/app/api/knowledge_map.py", "source_location": "L844"}, {"caller_nid": "knowledge_map_get_knowledge_map_entry_detail", "callee": "str", "source_file": "backend/app/api/knowledge_map.py", "source_location": "L848"}, {"caller_nid": "knowledge_map_get_knowledge_map_entry_detail", "callee": "next", "source_file": "backend/app/api/knowledge_map.py", "source_location": "L851"}, {"caller_nid": "knowledge_map_get_knowledge_map_entry_detail", "callee": "get", "source_file": "backend/app/api/knowledge_map.py", "source_location": "L854"}, {"caller_nid": "knowledge_map_get_knowledge_map_entry_detail", "callee": "normalize_translation_examples", "source_file": "backend/app/api/knowledge_map.py", "source_location": "L855"}, {"caller_nid": "knowledge_map_get_knowledge_map_entry_detail", "callee": "len", "source_file": "backend/app/api/knowledge_map.py", "source_location": "L857"}, {"caller_nid": "knowledge_map_get_knowledge_map_entry_detail", "callee": "find_example_links", "source_file": "backend/app/api/knowledge_map.py", "source_location": "L863"}, {"caller_nid": "knowledge_map_get_knowledge_map_entry_detail", "callee": "enumerate", "source_file": "backend/app/api/knowledge_map.py", "source_location": "L869"}, {"caller_nid": "knowledge_map_get_knowledge_map_entry_detail", "callee": "get", "source_file": "backend/app/api/knowledge_map.py", "source_location": "L869"}, {"caller_nid": "knowledge_map_get_knowledge_map_entry_detail", "callee": "str", "source_file": "backend/app/api/knowledge_map.py", "source_location": "L873"}, {"caller_nid": "knowledge_map_get_knowledge_map_entry_detail", "callee": "getattr", "source_file": "backend/app/api/knowledge_map.py", "source_location": "L876"}, {"caller_nid": "knowledge_map_get_knowledge_map_entry_detail", "callee": "normalize_translation_examples", "source_file": "backend/app/api/knowledge_map.py", "source_location": "L877"}, {"caller_nid": "knowledge_map_get_knowledge_map_entry_detail", "callee": "get", "source_file": "backend/app/api/knowledge_map.py", "source_location": "L879"}, {"caller_nid": "knowledge_map_get_knowledge_map_entry_detail", "callee": "str", "source_file": "backend/app/api/knowledge_map.py", "source_location": "L883"}, {"caller_nid": "knowledge_map_get_knowledge_map_entry_detail", "callee": "get", "source_file": "backend/app/api/knowledge_map.py", "source_location": "L887"}, {"caller_nid": "knowledge_map_get_knowledge_map_entry_detail", "callee": "list", "source_file": "backend/app/api/knowledge_map.py", "source_location": "L895"}, {"caller_nid": "knowledge_map_get_knowledge_map_entry_detail", "callee": "build_relation_groups", "source_file": "backend/app/api/knowledge_map.py", "source_location": "L897"}, {"caller_nid": "knowledge_map_get_knowledge_map_entry_detail", "callee": "resolve_exact_match_target", "source_file": "backend/app/api/knowledge_map.py", "source_location": "L905"}, {"caller_nid": "knowledge_map_get_knowledge_map_entry_detail", "callee": "normalize_confusable_words", "source_file": "backend/app/api/knowledge_map.py", "source_location": "L909"}, {"caller_nid": "knowledge_map_get_knowledge_map_entry_detail", "callee": "get", "source_file": "backend/app/api/knowledge_map.py", "source_location": "L914"}, {"caller_nid": "knowledge_map_get_knowledge_map_entry_detail", "callee": "get", "source_file": "backend/app/api/knowledge_map.py", "source_location": "L915"}, {"caller_nid": "knowledge_map_get_knowledge_map_entry_detail", "callee": "get", "source_file": "backend/app/api/knowledge_map.py", "source_location": "L916"}, {"caller_nid": "knowledge_map_get_knowledge_map_entry_detail", "callee": "get", "source_file": "backend/app/api/knowledge_map.py", "source_location": "L917"}, {"caller_nid": "knowledge_map_get_knowledge_map_entry_detail", "callee": "len", "source_file": "backend/app/api/knowledge_map.py", "source_location": "L936"}, {"caller_nid": "knowledge_map_get_knowledge_map_entry_detail", "callee": "execute", "source_file": "backend/app/api/knowledge_map.py", "source_location": "L940"}, {"caller_nid": "knowledge_map_get_knowledge_map_entry_detail", "callee": "where", "source_file": "backend/app/api/knowledge_map.py", "source_location": "L941"}, {"caller_nid": "knowledge_map_get_knowledge_map_entry_detail", "callee": "options", "source_file": "backend/app/api/knowledge_map.py", "source_location": "L941"}, {"caller_nid": "knowledge_map_get_knowledge_map_entry_detail", "callee": "select", "source_file": "backend/app/api/knowledge_map.py", "source_location": "L941"}, {"caller_nid": "knowledge_map_get_knowledge_map_entry_detail", "callee": "load_only", "source_file": "backend/app/api/knowledge_map.py", "source_location": "L943"}, {"caller_nid": "knowledge_map_get_knowledge_map_entry_detail", "callee": "scalar_one_or_none", "source_file": "backend/app/api/knowledge_map.py", "source_location": "L956"}, {"caller_nid": "knowledge_map_get_knowledge_map_entry_detail", "callee": "HTTPException", "source_file": "backend/app/api/knowledge_map.py", "source_location": "L958"}, {"caller_nid": "knowledge_map_get_knowledge_map_entry_detail", "callee": "get_status_row", "source_file": "backend/app/api/knowledge_map.py", "source_location": "L960"}, {"caller_nid": "knowledge_map_get_knowledge_map_entry_detail", "callee": "load_catalog_neighbors", "source_file": "backend/app/api/knowledge_map.py", "source_location": "L961"}, {"caller_nid": "knowledge_map_get_knowledge_map_entry_detail", "callee": "load_phrase_detail_rows", "source_file": "backend/app/api/knowledge_map.py", "source_location": "L962"}, {"caller_nid": "knowledge_map_get_knowledge_map_entry_detail", "callee": "values", "source_file": "backend/app/api/knowledge_map.py", "source_location": "L968"}, {"caller_nid": "knowledge_map_get_knowledge_map_entry_detail", "callee": "load_phrase_voice_assets", "source_file": "backend/app/api/knowledge_map.py", "source_location": "L969"}, {"caller_nid": "knowledge_map_get_knowledge_map_entry_detail", "callee": "collect_exact_lookup_terms", "source_file": "backend/app/api/knowledge_map.py", "source_location": "L975"}, {"caller_nid": "knowledge_map_get_knowledge_map_entry_detail", "callee": "list", "source_file": "backend/app/api/knowledge_map.py", "source_location": "L977"}, {"caller_nid": "knowledge_map_get_knowledge_map_entry_detail", "callee": "list", "source_file": "backend/app/api/knowledge_map.py", "source_location": "L978"}, {"caller_nid": "knowledge_map_get_knowledge_map_entry_detail", "callee": "list", "source_file": "backend/app/api/knowledge_map.py", "source_location": "L979"}, {"caller_nid": "knowledge_map_get_knowledge_map_entry_detail", "callee": "values", "source_file": "backend/app/api/knowledge_map.py", "source_location": "L981"}, {"caller_nid": "knowledge_map_get_knowledge_map_entry_detail", "callee": "load_entry_lookup_for_terms", "source_file": "backend/app/api/knowledge_map.py", "source_location": "L983"}, {"caller_nid": "knowledge_map_get_knowledge_map_entry_detail", "callee": "get", "source_file": "backend/app/api/knowledge_map.py", "source_location": "L986"}, {"caller_nid": "knowledge_map_get_knowledge_map_entry_detail", "callee": "append", "source_file": "backend/app/api/knowledge_map.py", "source_location": "L987"}, {"caller_nid": "knowledge_map_get_knowledge_map_entry_detail", "callee": "str", "source_file": "backend/app/api/knowledge_map.py", "source_location": "L989"}, {"caller_nid": "knowledge_map_get_knowledge_map_entry_detail", "callee": "list", "source_file": "backend/app/api/knowledge_map.py", "source_location": "L997"}, {"caller_nid": "knowledge_map_get_knowledge_map_entry_detail", "callee": "list", "source_file": "backend/app/api/knowledge_map.py", "source_location": "L998"}, {"caller_nid": "knowledge_map_get_knowledge_map_entry_detail", "callee": "resolve_exact_match_target", "source_file": "backend/app/api/knowledge_map.py", "source_location": "L1004"}, {"caller_nid": "knowledge_map_get_knowledge_map_entry_detail", "callee": "list", "source_file": "backend/app/api/knowledge_map.py", "source_location": "L1008"}, {"caller_nid": "knowledge_map_get_knowledge_map_entry_detail", "callee": "resolve_exact_match_target", "source_file": "backend/app/api/knowledge_map.py", "source_location": "L1015"}, {"caller_nid": "knowledge_map_get_knowledge_map_entry_detail", "callee": "list", "source_file": "backend/app/api/knowledge_map.py", "source_location": "L1019"}, {"caller_nid": "knowledge_map_get_knowledge_map_entry_detail", "callee": "resolve_exact_match_target", "source_file": "backend/app/api/knowledge_map.py", "source_location": "L1026"}, {"caller_nid": "knowledge_map_get_knowledge_map_entry_detail", "callee": "list", "source_file": "backend/app/api/knowledge_map.py", "source_location": "L1030"}, {"caller_nid": "knowledge_map_get_knowledge_map_entry_detail", "callee": "str", "source_file": "backend/app/api/knowledge_map.py", "source_location": "L1034"}, {"caller_nid": "knowledge_map_get_knowledge_map_entry_detail", "callee": "find_example_links", "source_file": "backend/app/api/knowledge_map.py", "source_location": "L1044"}, {"caller_nid": "knowledge_map_get_knowledge_map_entry_detail", "callee": "get", "source_file": "backend/app/api/knowledge_map.py", "source_location": "L1051"}, {"caller_nid": "knowledge_map_get_knowledge_map_entry_detail", "callee": "get", "source_file": "backend/app/api/knowledge_map.py", "source_location": "L1059"}, {"caller_nid": "knowledge_map_get_knowledge_map_entry_detail", "callee": "get_entry_queue_schedule", "source_file": "backend/app/api/knowledge_map.py", "source_location": "L1062"}, {"caller_nid": "knowledge_map_get_knowledge_map_entry_detail", "callee": "ReviewService", "source_file": "backend/app/api/knowledge_map.py", "source_location": "L1062"}, {"caller_nid": "knowledge_map_get_knowledge_map_entry_detail", "callee": "str", "source_file": "backend/app/api/knowledge_map.py", "source_location": "L1070"}, {"caller_nid": "knowledge_map_get_knowledge_map_entry_detail", "callee": "int", "source_file": "backend/app/api/knowledge_map.py", "source_location": "L1073"}, {"caller_nid": "knowledge_map_get_knowledge_map_entry_detail", "callee": "list", "source_file": "backend/app/api/knowledge_map.py", "source_location": "L1080"}, {"caller_nid": "knowledge_map_get_knowledge_map_entry_detail", "callee": "get", "source_file": "backend/app/api/knowledge_map.py", "source_location": "L1089"}, {"caller_nid": "knowledge_map_get_knowledge_map_entry_detail", "callee": "get", "source_file": "backend/app/api/knowledge_map.py", "source_location": "L1090"}, {"caller_nid": "knowledge_map_get_knowledge_map_entry_detail", "callee": "get", "source_file": "backend/app/api/knowledge_map.py", "source_location": "L1091"}, {"caller_nid": "knowledge_map_get_knowledge_map_entry_detail", "callee": "get", "source_file": "backend/app/api/knowledge_map.py", "source_location": "L1092"}, {"caller_nid": "knowledge_map_get_knowledge_map_entry_detail", "callee": "len", "source_file": "backend/app/api/knowledge_map.py", "source_location": "L1111"}, {"caller_nid": "knowledge_map_put_knowledge_map_status", "callee": "HTTPException", "source_file": "backend/app/api/knowledge_map.py", "source_location": "L1127"}, {"caller_nid": "knowledge_map_put_knowledge_map_status", "callee": "perf_counter", "source_file": "backend/app/api/knowledge_map.py", "source_location": "L1129"}, {"caller_nid": "knowledge_map_put_knowledge_map_status", "callee": "execute", "source_file": "backend/app/api/knowledge_map.py", "source_location": "L1131"}, {"caller_nid": "knowledge_map_put_knowledge_map_status", "callee": "where", "source_file": "backend/app/api/knowledge_map.py", "source_location": "L1131"}, {"caller_nid": "knowledge_map_put_knowledge_map_status", "callee": "select", "source_file": "backend/app/api/knowledge_map.py", "source_location": "L1131"}, {"caller_nid": "knowledge_map_put_knowledge_map_status", "callee": "scalar_one_or_none", "source_file": "backend/app/api/knowledge_map.py", "source_location": "L1132"}, {"caller_nid": "knowledge_map_put_knowledge_map_status", "callee": "HTTPException", "source_file": "backend/app/api/knowledge_map.py", "source_location": "L1134"}, {"caller_nid": "knowledge_map_put_knowledge_map_status", "callee": "get_status_row", "source_file": "backend/app/api/knowledge_map.py", "source_location": "L1136"}, {"caller_nid": "knowledge_map_put_knowledge_map_status", "callee": "LearnerEntryStatus", "source_file": "backend/app/api/knowledge_map.py", "source_location": "L1138"}, {"caller_nid": "knowledge_map_put_knowledge_map_status", "callee": "add", "source_file": "backend/app/api/knowledge_map.py", "source_location": "L1144"}, {"caller_nid": "knowledge_map_put_knowledge_map_status", "callee": "_ensure_learning_entry_has_review_state", "source_file": "backend/app/api/knowledge_map.py", "source_location": "L1148"}, {"caller_nid": "knowledge_map_put_knowledge_map_status", "callee": "ReviewService", "source_file": "backend/app/api/knowledge_map.py", "source_location": "L1148"}, {"caller_nid": "knowledge_map_put_knowledge_map_status", "callee": "commit", "source_file": "backend/app/api/knowledge_map.py", "source_location": "L1153"}, {"caller_nid": "knowledge_map_put_knowledge_map_status", "callee": "str", "source_file": "backend/app/api/knowledge_map.py", "source_location": "L1161"}, {"caller_nid": "knowledge_map_search_knowledge_map", "callee": "perf_counter", "source_file": "backend/app/api/knowledge_map.py", "source_location": "L1172"}, {"caller_nid": "knowledge_map_search_knowledge_map", "callee": "build_catalog", "source_file": "backend/app/api/knowledge_map.py", "source_location": "L1173"}, {"caller_nid": "knowledge_map_search_knowledge_map", "callee": "len", "source_file": "backend/app/api/knowledge_map.py", "source_location": "L1180"}, {"caller_nid": "knowledge_map_get_search_history", "callee": "perf_counter", "source_file": "backend/app/api/knowledge_map.py", "source_location": "L1192"}, {"caller_nid": "knowledge_map_get_search_history", "callee": "list_search_history", "source_file": "backend/app/api/knowledge_map.py", "source_location": "L1193"}, {"caller_nid": "knowledge_map_get_search_history", "callee": "len", "source_file": "backend/app/api/knowledge_map.py", "source_location": "L1199"}, {"caller_nid": "knowledge_map_get_search_history", "callee": "str", "source_file": "backend/app/api/knowledge_map.py", "source_location": "L1206"}, {"caller_nid": "knowledge_map_get_search_history", "callee": "isoformat", "source_file": "backend/app/api/knowledge_map.py", "source_location": "L1207"}, {"caller_nid": "knowledge_map_post_search_history", "callee": "perf_counter", "source_file": "backend/app/api/knowledge_map.py", "source_location": "L1222"}, {"caller_nid": "knowledge_map_post_search_history", "callee": "execute", "source_file": "backend/app/api/knowledge_map.py", "source_location": "L1223"}, {"caller_nid": "knowledge_map_post_search_history", "callee": "where", "source_file": "backend/app/api/knowledge_map.py", "source_location": "L1224"}, {"caller_nid": "knowledge_map_post_search_history", "callee": "select", "source_file": "backend/app/api/knowledge_map.py", "source_location": "L1224"}, {"caller_nid": "knowledge_map_post_search_history", "callee": "scalar_one_or_none", "source_file": "backend/app/api/knowledge_map.py", "source_location": "L1229"}, {"caller_nid": "knowledge_map_post_search_history", "callee": "SearchHistory", "source_file": "backend/app/api/knowledge_map.py", "source_location": "L1231"}, {"caller_nid": "knowledge_map_post_search_history", "callee": "UUID", "source_file": "backend/app/api/knowledge_map.py", "source_location": "L1235"}, {"caller_nid": "knowledge_map_post_search_history", "callee": "add", "source_file": "backend/app/api/knowledge_map.py", "source_location": "L1237"}, {"caller_nid": "knowledge_map_post_search_history", "callee": "UUID", "source_file": "backend/app/api/knowledge_map.py", "source_location": "L1240"}, {"caller_nid": "knowledge_map_post_search_history", "callee": "commit", "source_file": "backend/app/api/knowledge_map.py", "source_location": "L1241"}, {"caller_nid": "knowledge_map_post_search_history", "callee": "str", "source_file": "backend/app/api/knowledge_map.py", "source_location": "L1252"}, {"caller_nid": "knowledge_map_post_search_history", "callee": "isoformat", "source_file": "backend/app/api/knowledge_map.py", "source_location": "L1253"}]}