{"nodes": [{"id": "backend_app_models_phrase_sense_py", "label": "phrase_sense.py", "file_type": "code", "source_file": "backend/app/models/phrase_sense.py", "source_location": "L1"}, {"id": "phrase_sense_phrasesense", "label": "PhraseSense", "file_type": "code", "source_file": "backend/app/models/phrase_sense.py", "source_location": "L19"}, {"id": "base", "label": "Base", "file_type": "code", "source_file": "", "source_location": ""}, {"id": "phrase_sense_phrasesense_init", "label": ".__init__()", "file_type": "code", "source_file": "backend/app/models/phrase_sense.py", "source_location": "L73"}, {"id": "phrase_sense_phrasesense_repr", "label": ".__repr__()", "file_type": "code", "source_file": "backend/app/models/phrase_sense.py", "source_location": "L78"}], "edges": [{"source": "backend_app_models_phrase_sense_py", "target": "uuid", "relation": "imports", "confidence": "EXTRACTED", "source_file": "backend/app/models/phrase_sense.py", "source_location": "L1", "weight": 1.0}, {"source": "backend_app_models_phrase_sense_py", "target": "datetime", "relation": "imports_from", "confidence": "EXTRACTED", "source_file": "backend/app/models/phrase_sense.py", "source_location": "L2", "weight": 1.0}, {"source": "backend_app_models_phrase_sense_py", "target": "typing", "relation": "imports_from", "confidence": "EXTRACTED", "source_file": "backend/app/models/phrase_sense.py", "source_location": "L3", "weight": 1.0}, {"source": "backend_app_models_phrase_sense_py", "target": "sqlalchemy", "relation": "imports_from", "confidence": "EXTRACTED", "source_file": "backend/app/models/phrase_sense.py", "source_location": "L5", "weight": 1.0}, {"source": "backend_app_models_phrase_sense_py", "target": "sqlalchemy_dialects_postgresql", "relation": "imports_from", "confidence": "EXTRACTED", "source_file": "backend/app/models/phrase_sense.py", "source_location": "L6", "weight": 1.0}, {"source": "backend_app_models_phrase_sense_py", "target": "sqlalchemy_orm", "relation": "imports_from", "confidence": "EXTRACTED", "source_file": "backend/app/models/phrase_sense.py", "source_location": "L7", "weight": 1.0}, {"source": "backend_app_models_phrase_sense_py", "target": "app_core_database", "relation": "imports_from", "confidence": "EXTRACTED", "source_file": "backend/app/models/phrase_sense.py", "source_location": "L9", "weight": 1.0}, {"source": "backend_app_models_phrase_sense_py", "target": "app_models_schema_names", "relation": "imports_from", "confidence": "EXTRACTED", "source_file": "backend/app/models/phrase_sense.py", "source_location": "L10", "weight": 1.0}, {"source": "backend_app_models_phrase_sense_py", "target": "app_models_lexicon_voice_asset", "relation": "imports_from", "confidence": "EXTRACTED", "source_file": "backend/app/models/phrase_sense.py", "source_location": "L13", "weight": 1.0}, {"source": "backend_app_models_phrase_sense_py", "target": "app_models_phrase_entry", "relation": "imports_from", "confidence": "EXTRACTED", "source_file": "backend/app/models/phrase_sense.py", "source_location": "L14", "weight": 1.0}, {"source": "backend_app_models_phrase_sense_py", "target": "app_models_phrase_sense_example", "relation": "imports_from", "confidence": "EXTRACTED", "source_file": "backend/app/models/phrase_sense.py", "source_location": "L15", "weight": 1.0}, {"source": "backend_app_models_phrase_sense_py", "target": "app_models_phrase_sense_localization", "relation": "imports_from", "confidence": "EXTRACTED", "source_file": "backend/app/models/phrase_sense.py", "source_location": "L16", "weight": 1.0}, {"source": "backend_app_models_phrase_sense_py", "target": "phrase_sense_phrasesense", "relation": "contains", "confidence": "EXTRACTED", "source_file": "backend/app/models/phrase_sense.py", "source_location": "L19", "weight": 1.0}, {"source": "phrase_sense_phrasesense", "target": "base", "relation": "inherits", "confidence": "EXTRACTED", "source_file": "backend/app/models/phrase_sense.py", "source_location": "L19", "weight": 1.0}, {"source": "phrase_sense_phrasesense", "target": "phrase_sense_phrasesense_init", "relation": "method", "confidence": "EXTRACTED", "source_file": "backend/app/models/phrase_sense.py", "source_location": "L73", "weight": 1.0}, {"source": "phrase_sense_phrasesense", "target": "phrase_sense_phrasesense_repr", "relation": "method", "confidence": "EXTRACTED", "source_file": "backend/app/models/phrase_sense.py", "source_location": "L78", "weight": 1.0}]}